pyfoobeef/__init__.py
pyfoobeef/async_client.py
pyfoobeef/client.py
pyfoobeef/endpoints.py
pyfoobeef/event_listener.py
pyfoobeef/exceptions.py
pyfoobeef/helper_funcs.py
pyfoobeef/models.py
pyfoobeef/type_helpers.py
pyfoobeef-0.9.0.4.dist-info/LICENSE
pyfoobeef-0.9.0.4.dist-info/METADATA
pyfoobeef-0.9.0.4.dist-info/WHEEL
pyfoobeef-0.9.0.4.dist-info/top_level.txt
pyfoobeef-0.9.0.4.dist-info/RECORD
