Metadata-Version: 2.1
Name: pyfoobeef
Version: 0.9.0.4
Summary: Allows control of the Foobar2000 and DeaDBeeF media players in Python through the beefweb plugin.
Home-page: https://github.com/Ada-Kru/pyfoobeef
Author: Adam Krueger
Author-email: adamkru@gmail.com
License: UNKNOWN
Keywords: Foobar2000 DeaDBeeF Media Player Beefweb Music Audio
Platform: UNKNOWN
Classifier: Programming Language :: Python :: 3
Classifier: License :: OSI Approved :: MIT License
Classifier: Operating System :: OS Independent
Classifier: Intended Audience :: Developers
Classifier: Natural Language :: English
Requires-Python: >=3.6
Requires-Dist: urllib3
Requires-Dist: aiohttp (>=3)
Requires-Dist: aiohttp-sse-client
